[
  {
    "id": "rec6Wp39V8DKteoSX",
    "orderNumber": "ENT69-0009-23/03/2022",
    "dateLivraison": "24 mars 2022",
    "dateLivraison2": "24/03/2022",
    "statut": "Livrée",
    "totalAmount": 330.49
  },
  {
    "id": "rec6lYtJ82750ix4q",
    "orderNumber": "PRO69-0006-11/12/2021",
    "dateLivraison": "14 déc. 2021",
    "dateLivraison2": "14/12/2021",
    "statut": "Livrée",
    "totalAmount": 182.84
  },
  {
    "id": "recMrxrcPrVbWyjez",
    "orderNumber": "PRO69-0006-04/04/2022",
    "dateLivraison": "5 avr. 2022",
    "dateLivraison2": "05/04/2022",
    "statut": "Annulée",
    "totalAmount": 104.66
  },
  {
    "id": "recTi2VRdUSnXyWzr",
    "orderNumber": "PRO69-0007-15/12/2021",
    "dateLivraison": "16 déc. 2021",
    "dateLivraison2": "16/12/2021",
    "statut": "Livrée",
    "totalAmount": 89.55
  },
  {
    "id": "recar1aUmauAhKHgY",
    "orderNumber": "ENT69-0009-15/02/2022",
    "dateLivraison": "17 févr. 2022",
    "dateLivraison2": "17/02/2022",
    "statut": "Livrée",
    "totalAmount": 11.03
  },
  {
    "id": "recbtEcClO2aicYBH",
    "orderNumber": "PRO69-0006-07/02/2022",
    "dateLivraison": "8 févr. 2022",
    "dateLivraison2": "08/02/2022",
    "statut": "Livrée",
    "totalAmount": 152.33
  },
  {
    "id": "reccP2VzjQAwlHnqn",
    "orderNumber": "PRO69-0007-14/05/2022",
    "dateLivraison": "17 mai 2022",
    "dateLivraison2": "17/05/2022",
    "statut": "Livrée",
    "totalAmount": 77.11
  },
  {
    "id": "recf1x1MrHFswzAGy",
    "orderNumber": "PRO69-0007-06/01/2022",
    "dateLivraison": "11 janv. 2022",
    "dateLivraison2": "11/01/2022",
    "statut": "Livrée",
    "totalAmount": 20.49
  },
  {
    "id": "recgrfp166yMJMvID",
    "orderNumber": "PRO69-0007-15/03/2022",
    "dateLivraison": "17 mars 2022",
    "dateLivraison2": "17/03/2022",
    "statut": "Livrée",
    "totalAmount": 69.64
  }
]
